toytree/__init__.py
toytree/annotate/__init__.py
toytree/annotate/src/__init__.py
toytree/annotate/src/add_admixture_edge.py
toytree/annotate/src/add_axes_box_outline.py
toytree/annotate/src/add_color_scale.py
toytree/annotate/src/add_edge_markers.py
toytree/annotate/src/add_node_markers.py
toytree/annotate/src/add_pie_markers.py
toytree/annotate/src/add_scale_bar.py
toytree/annotate/src/add_tip_markers.py
toytree/annotate/src/checks.py
toytree/annotate/src/image_api.py
toytree/cli/__init__.py
toytree/cli/main.py
toytree/color/__init__.py
toytree/color/src/__init__.py
toytree/color/src/colorkit.py
toytree/color/src/concat.py
toytree/color/src/toycolor.py
toytree/color/src/utils.py
toytree/core/__init__.py
toytree/core/apis.py
toytree/core/multitree.py
toytree/core/node.py
toytree/core/tree.py
toytree/data/__init__.py
toytree/data/_src/__init__.py
toytree/data/_src/data.py
toytree/data/_src/expand_node_mapping.py
toytree/data/_src/get_node_data.py
toytree/data/_src/set_node_data.py
toytree/distance/__init__.py
toytree/distance/_src/__init__.py
toytree/distance/_src/nodedist.py
toytree/distance/_src/quartet_dist.py
toytree/distance/_src/tree_move_dists.py
toytree/distance/_src/treedist.py
toytree/distance/_src/treedist_sample.py
toytree/distance/_src/treedist_utils.py
toytree/drawing/__init__.py
toytree/drawing/src/__init__.py
toytree/drawing/src/draw_cloudtree.py
toytree/drawing/src/draw_demography.py
toytree/drawing/src/draw_multitree.py
toytree/drawing/src/draw_toytree.py
toytree/drawing/src/mark_annotation.py
toytree/drawing/src/mark_pie.py
toytree/drawing/src/mark_polygon.py
toytree/drawing/src/mark_toytree.py
toytree/drawing/src/render_annotation.py
toytree/drawing/src/render_marker.py
toytree/drawing/src/render_pie.py
toytree/drawing/src/render_text.py
toytree/drawing/src/render_tree.py
toytree/drawing/src/setup_canvas.py
toytree/drawing/src/setup_grid.py
toytree/enum/__init__.py
toytree/enum/src/__init__.py
toytree/enum/src/bipartitions.py
toytree-3.0.7.dist-info/LICENSE.txt
toytree-3.0.7.dist-info/METADATA
toytree-3.0.7.dist-info/WHEEL
toytree-3.0.7.dist-info/entry_points.txt
toytree-3.0.7.dist-info/top_level.txt
toytree-3.0.7.dist-info/RECORD
