Metadata-Version: 2.2
Name: toytree
Version: 3.0.7
Summary: tree manipulation, plotting, and evolutionary analysis library
Home-page: https://eaton-lab.org/toytree
Author: Deren Eaton
Author-email: de2356@columbia.edu
License: GPL
Keywords: phylogeny,tree,network,plotting,toyplot,SVG,HTML,Genealogy,Coalescent
Classifier: Programming Language :: Python :: 3
Classifier: License :: OSI Approved :: GNU General Public License v3 (GPLv3)
Requires-Python: >=3.7
License-File: LICENSE.txt
Requires-Dist: numpy
Requires-Dist: scipy
Requires-Dist: pandas
Requires-Dist: loguru
Requires-Dist: requests
Requires-Dist: toyplot
Provides-Extra: dev
Requires-Dist: black==22.1.0; extra == "dev"
Requires-Dist: flake8==4.0.1; extra == "dev"
